[{"name":"__vtins__3K42TrT29UPZMxpy","value":"%7B%22sid%22%3A%20%2218c1bad3-ec13-59df-8a14-331f0e2d25d0%22%2C%20%22vd%22%3A%201%2C%20%22stt%22%3A%200%2C%20%22dr%22%3A%200%2C%20%22expires%22%3A%201743364290450%2C%20%22ct%22%3A%201743362490450%7D","domain":"glupcvv.co","path":"/","expires":-1,"httpOnly":false,"secure":false,"sameSite":"Lax"},{"name":"__51uvsct__3K42TrT29UPZMxpy","value":"1","domain":"glupcvv.co","path":"/","expires":1777922490.456988,"httpOnly":false,"secure":false,"sameSite":"Lax"},{"name":"__51vcke__3K42TrT29UPZMxpy","value":"41d54704-d1a6-5576-9ffe-6a63531807ef","domain":"glupcvv.co","path":"/","expires":1777922490.459375,"httpOnly":false,"secure":false,"sameSite":"Lax"},{"name":"__51vuft__3K42TrT29UPZMxpy","value":"1743362490459","domain":"glupcvv.co","path":"/","expires":1777922490.459542,"httpOnly":false,"secure":false,"sameSite":"Lax"},{"name":"captcha","value":"wYLNsckUdDKPXq9u%2Bnu2tw%3D%3D","domain":"glupcvv.co","path":"/","expires":1743362798.769368,"httpOnly":true,"secure":true,"sameSite":"Lax"},{"name":"session","value":"JIvTaeYMILUWALb8YDCxIw%3D%3D","domain":"glupcvv.co","path":"/","expires":1743967301.923826,"httpOnly":true,"secure":true,"sameSite":"Lax"},{"name":"u","value":"g61%2FEvirSLyY44j2gEcskw%3D%3D","domain":"glupcvv.co","path":"/","expires":1743967301.923931,"httpOnly":true,"secure":true,"sameSite":"Lax"}]