[{"name":"captcha","value":"LPxms9malOb3eoCUR3cNMw%3D%3D","domain":"glupcvv.co","path":"/","expires":1744167851.611682,"httpOnly":true,"secure":true,"sameSite":"Lax"},{"name":"__vtins__3K42TrT29UPZMxpy","value":"%7B%22sid%22%3A%20%2230b732f1-749c-5c9f-b8da-c73b3dc5d457%22%2C%20%22vd%22%3A%201%2C%20%22stt%22%3A%200%2C%20%22dr%22%3A%200%2C%20%22expires%22%3A%201744169352656%2C%20%22ct%22%3A%201744167552656%7D","domain":"glupcvv.co","path":"/","expires":-1,"httpOnly":false,"secure":false,"sameSite":"Lax"},{"name":"__51uvsct__3K42TrT29UPZMxpy","value":"1","domain":"glupcvv.co","path":"/","expires":1778727552.660686,"httpOnly":false,"secure":false,"sameSite":"Lax"},{"name":"__51vcke__3K42TrT29UPZMxpy","value":"7d8b61d3-7f18-5db1-9592-278448a5a64f","domain":"glupcvv.co","path":"/","expires":1778727552.66362,"httpOnly":false,"secure":false,"sameSite":"Lax"},{"name":"__51vuft__3K42TrT29UPZMxpy","value":"1744167552663","domain":"glupcvv.co","path":"/","expires":1778727552.66381,"httpOnly":false,"secure":false,"sameSite":"Lax"},{"name":"session","value":"SpH3UypVHwW28QviYnLH3g%3D%3D","domain":"glupcvv.co","path":"/","expires":1744772357.333983,"httpOnly":true,"secure":true,"sameSite":"Lax"},{"name":"u","value":"myFNods3zLyZhdYByO1rLw%3D%3D","domain":"glupcvv.co","path":"/","expires":1744772357.334066,"httpOnly":true,"secure":true,"sameSite":"Lax"}]