[{"name":"captcha","value":"FauGbczj%2B4mMXk1wEhVf1A%3D%3D","domain":"glupcvv.co","path":"/","expires":1742845128.458882,"httpOnly":true,"secure":true,"sameSite":"Lax"},{"name":"__vtins__3K42TrT29UPZMxpy","value":"%7B%22sid%22%3A%20%22245b0d19-a500-54f9-afc1-ef90be8da190%22%2C%20%22vd%22%3A%201%2C%20%22stt%22%3A%200%2C%20%22dr%22%3A%200%2C%20%22expires%22%3A%201742846629717%2C%20%22ct%22%3A%201742844829717%7D","domain":"glupcvv.co","path":"/","expires":-1,"httpOnly":false,"secure":false,"sameSite":"Lax"},{"name":"__51uvsct__3K42TrT29UPZMxpy","value":"1","domain":"glupcvv.co","path":"/","expires":1777404829.720517,"httpOnly":false,"secure":false,"sameSite":"Lax"},{"name":"__51vcke__3K42TrT29UPZMxpy","value":"45d194ea-3a48-54d9-8182-8fbec89ff5fd","domain":"glupcvv.co","path":"/","expires":1777404829.721983,"httpOnly":false,"secure":false,"sameSite":"Lax"},{"name":"__51vuft__3K42TrT29UPZMxpy","value":"1742844829721","domain":"glupcvv.co","path":"/","expires":1777404829.722098,"httpOnly":false,"secure":false,"sameSite":"Lax"},{"name":"session","value":"3DkdlLQZmkPsr%2BVgUu2Tbg%3D%3D","domain":"glupcvv.co","path":"/","expires":1743449635.293812,"httpOnly":true,"secure":true,"sameSite":"Lax"},{"name":"u","value":"Z2MR83cM85k505EG3bOW%2BA%3D%3D","domain":"glupcvv.co","path":"/","expires":1743449635.293906,"httpOnly":true,"secure":true,"sameSite":"Lax"}]