[{"name":"__vtins__3K42TrT29UPZMxpy","value":"%7B%22sid%22%3A%20%2262b69362-bca1-5312-827c-42b18c127590%22%2C%20%22vd%22%3A%201%2C%20%22stt%22%3A%200%2C%20%22dr%22%3A%200%2C%20%22expires%22%3A%201742775395695%2C%20%22ct%22%3A%201742773595695%7D","domain":"glupcvv.co","path":"/","expires":-1,"httpOnly":false,"secure":false,"sameSite":"Lax"},{"name":"__51uvsct__3K42TrT29UPZMxpy","value":"1","domain":"glupcvv.co","path":"/","expires":1777333595.698688,"httpOnly":false,"secure":false,"sameSite":"Lax"},{"name":"__51vcke__3K42TrT29UPZMxpy","value":"92aeeb43-a6f7-5e0e-affc-fc83cfb8a471","domain":"glupcvv.co","path":"/","expires":1777333595.700128,"httpOnly":false,"secure":false,"sameSite":"Lax"},{"name":"__51vuft__3K42TrT29UPZMxpy","value":"1742773595700","domain":"glupcvv.co","path":"/","expires":1777333595.70025,"httpOnly":false,"secure":false,"sameSite":"Lax"},{"name":"captcha","value":"s0kq0L3%2FLPBXkILNQdJ0Rw%3D%3D","domain":"glupcvv.co","path":"/","expires":1742773900.512,"httpOnly":true,"secure":true,"sameSite":"Lax"},{"name":"session","value":"6bvDwHPItwjPfkIHFnwzlg%3D%3D","domain":"glupcvv.co","path":"/","expires":1743378403.655848,"httpOnly":true,"secure":true,"sameSite":"Lax"},{"name":"u","value":"cWEFDzoNrtVhBhfu7W%2Bltw%3D%3D","domain":"glupcvv.co","path":"/","expires":1743378403.655916,"httpOnly":true,"secure":true,"sameSite":"Lax"}]