[{"name":"__vtins__3K42TrT29UPZMxpy","value":"%7B%22sid%22%3A%20%221f0f1356-efec-5f3d-93f8-ee6549c692ec%22%2C%20%22vd%22%3A%201%2C%20%22stt%22%3A%200%2C%20%22dr%22%3A%200%2C%20%22expires%22%3A%201742847515164%2C%20%22ct%22%3A%201742845715164%7D","domain":"glupcvv.co","path":"/","expires":-1,"httpOnly":false,"secure":false,"sameSite":"Lax"},{"name":"__51uvsct__3K42TrT29UPZMxpy","value":"1","domain":"glupcvv.co","path":"/","expires":1777405715.168324,"httpOnly":false,"secure":false,"sameSite":"Lax"},{"name":"__51vcke__3K42TrT29UPZMxpy","value":"64cf9ed3-3b13-5ef1-b25d-7aff8f0da813","domain":"glupcvv.co","path":"/","expires":1777405715.169827,"httpOnly":false,"secure":false,"sameSite":"Lax"},{"name":"__51vuft__3K42TrT29UPZMxpy","value":"1742845715169","domain":"glupcvv.co","path":"/","expires":1777405715.169974,"httpOnly":false,"secure":false,"sameSite":"Lax"},{"name":"captcha","value":"9mKfaHVB4JUJlB2j46dDTA%3D%3D","domain":"glupcvv.co","path":"/","expires":1742846020.249365,"httpOnly":true,"secure":true,"sameSite":"Lax"},{"name":"session","value":"EmwoQ8Y75r6yPPaKp5r9GQ%3D%3D","domain":"glupcvv.co","path":"/","expires":1743450523.742184,"httpOnly":true,"secure":true,"sameSite":"Lax"},{"name":"u","value":"6%2F0aXhOFtIjBmoJID%2FnHdQ%3D%3D","domain":"glupcvv.co","path":"/","expires":1743450523.742251,"httpOnly":true,"secure":true,"sameSite":"Lax"}]