[{"name":"captcha","value":"WCkXqj%2BZ5cV7OqOSIa6PdA%3D%3D","domain":"glupcvv.co","path":"/","expires":1742845756.781738,"httpOnly":true,"secure":true,"sameSite":"Lax"},{"name":"__vtins__3K42TrT29UPZMxpy","value":"%7B%22sid%22%3A%20%2206049046-6e38-540b-aa11-dcd16ab28513%22%2C%20%22vd%22%3A%201%2C%20%22stt%22%3A%200%2C%20%22dr%22%3A%200%2C%20%22expires%22%3A%201742847257966%2C%20%22ct%22%3A%201742845457966%7D","domain":"glupcvv.co","path":"/","expires":-1,"httpOnly":false,"secure":false,"sameSite":"Lax"},{"name":"__51uvsct__3K42TrT29UPZMxpy","value":"1","domain":"glupcvv.co","path":"/","expires":1777405457.970057,"httpOnly":false,"secure":false,"sameSite":"Lax"},{"name":"__51vcke__3K42TrT29UPZMxpy","value":"953f700d-8d7a-5a94-9838-358b60311293","domain":"glupcvv.co","path":"/","expires":1777405457.971553,"httpOnly":false,"secure":false,"sameSite":"Lax"},{"name":"__51vuft__3K42TrT29UPZMxpy","value":"1742845457971","domain":"glupcvv.co","path":"/","expires":1777405457.971707,"httpOnly":false,"secure":false,"sameSite":"Lax"},{"name":"session","value":"hlZVi7vlxN51x%2FjGwB6JiA%3D%3D","domain":"glupcvv.co","path":"/","expires":1743450263.807797,"httpOnly":true,"secure":true,"sameSite":"Lax"},{"name":"u","value":"Dq2fxwOFRjdH7XhHJjfrag%3D%3D","domain":"glupcvv.co","path":"/","expires":1743450263.807863,"httpOnly":true,"secure":true,"sameSite":"Lax"}]